{
	"uniqueIdentifier": "ab774b12-f631-4adb-be4b-8425eb036992",
	"name": "Mai Tai",
	"description": "Všechny přísady a led kromě tmavého rumu a grenadiny přidejte do shakeru. Krátce protřepejte a slijte do sklenice. Až nakonec přidejte led a tmavý rum s grenadinou a dozdobte.",
	"noOfIngrediences": 6,
	"servings": 1,
	"image": "ab774b12-f631-4adb-be4b-8425eb036992.jpg",
	"ingredients": [
		{
			"name": "Limetková šťáva",
			"description": "",
			"amount": 5,
			"unitUniqueIdentifier": "eaf45597-88cb-43a8-8a53-9464cf76dd5c"
		},
		{
			"name": "Curacao",
			"description": "",
			"amount": 5,
			"unitUniqueIdentifier": "eaf45597-88cb-43a8-8a53-9464cf76dd5c"
		},
		{
			"name": "Světlý rum",
			"description": "",
			"amount": 5,
			"unitUniqueIdentifier": "eaf45597-88cb-43a8-8a53-9464cf76dd5c"
		},
		{
			"name": "Mandlový sirup",
			"description": "",
			"amount": 5,
			"unitUniqueIdentifier": "eaf45597-88cb-43a8-8a53-9464cf76dd5c"
		},
		{
			"name": "Tmavý rum",
			"description": "cukr a voda v poměru 1:1",
			"amount": 5,
			"unitUniqueIdentifier": "eaf45597-88cb-43a8-8a53-9464cf76dd5c"
		},
		{
			"name": "Grenadina",
			"description": "",
			"amount": 1,
			"unitUniqueIdentifier": "eaf45597-88cb-43a8-8a53-9464cf76dd5c"
		}
	]
}